safety_kit_pkg/__init__.py
safety_kit_pkg/safety.py
x23203137-0.0.1.dist-info/METADATA
x23203137-0.0.1.dist-info/WHEEL
x23203137-0.0.1.dist-info/top_level.txt
x23203137-0.0.1.dist-info/RECORD
