Metadata-Version: 2.1
Name: x23203137
Version: 0.0.1
Summary: Package for ridersclub
Home-page: https://github.com/x23203137/riders_safety
Author: arun
Author-email: arunshaji209@gmail.com
Classifier: Programming Language :: Python :: 3
Classifier: License :: OSI Approved :: MIT License
Classifier: Operating System :: OS Independent
Requires-Python: >=3.6
